pypierrat/__init__.py
pypierrat/dfconverter.py
pypierrat/mapdata.py
pypierrat-0.0.24.dist-info/LICENSE
pypierrat-0.0.24.dist-info/METADATA
pypierrat-0.0.24.dist-info/WHEEL
pypierrat-0.0.24.dist-info/top_level.txt
pypierrat-0.0.24.dist-info/RECORD
