Metadata-Version: 2.1
Name: pypierrat
Version: 0.0.24
Summary: My Personnal Python3 Package
Home-page: https://github.com/JulesPierrat/pypierrat
Author: Jules Pierrat
Author-email: jules.pierrat.98@gmail.com
Classifier: Programming Language :: Python :: 3
Classifier: License :: OSI Approved :: MIT License
Classifier: Operating System :: OS Independent
Requires-Python: >=3.6
License-File: LICENSE
